{
    "schemaVersion": 1,
    "id": "chatspliter",
    "version": "${version}",
    "name": "ChatSpliter",
    "description": "Split vanilla chat into multiple independent HUDs with keyword filtering",
    "authors": ["ChatSpliter"],
    "contact": {},
    "license": "MIT",
    "icon": "assets/chatspliter/icon.png",
    "environment": "client",
    "entrypoints": {
        "client": [
            "com.chatspliter.ChatSpliterMod"
        ]
    },
    "mixins": [
        "chatspliter.mixins.json"
    ],
    "depends": {
        "fabricloader": ">=0.16.9",
        "minecraft": "~1.21.8",
        "java": ">=21"
    }
}
